setup.py
django_uploads.egg-info/PKG-INFO
django_uploads.egg-info/SOURCES.txt
django_uploads.egg-info/dependency_links.txt
django_uploads.egg-info/top_level.txt
uploads/__init__.py
uploads/admin.py
uploads/app_settings.py
uploads/forms.py
uploads/models.py
uploads/templatetags/__init__.py
uploads/templatetags/uploads_tags.py