Metadata-Version: 1.0
Name: django-uploads
Version: 0.1-beta
Summary: A Django pluggable application to attach files to objects
Home-page: http://github.com/marinho/django-uploads/
Author: Marinho Brandao
Author-email: marinho@gmail.com
License: GNU Lesser General Public License (LGPL)
Platform: UNKNOWN
